quintessence_cell_engine/__init__.py
quintessence_cell_engine-0.0.0.dist-info/METADATA
quintessence_cell_engine-0.0.0.dist-info/WHEEL
quintessence_cell_engine-0.0.0.dist-info/top_level.txt
quintessence_cell_engine-0.0.0.dist-info/RECORD
