Metadata-Version: 2.1
Name: quintessence-cell-engine
Version: 0.0.0
Summary: Engine
Home-page: https://github.com/QuintessenceLabs/cell_engine
Author: Michael E. Vinyard
Author-email: mvinyard.ai@gmail.com
License: MIT
Classifier: Development Status :: 2 - Pre-Alpha
Classifier: Programming Language :: Python :: 3.9
Classifier: Intended Audience :: Science/Research
Classifier: Topic :: Scientific/Engineering :: Bio-Informatics
Requires-Python: >3.9.0
Requires-Dist: ABCParse >=0.0.6
